setup.cfg
setup.py
RPyBeacon/RPyBeacon.py
RPyBeacon/__init__.py
RPyBeacon/__main__.py
RPyBeacon.egg-info/PKG-INFO
RPyBeacon.egg-info/SOURCES.txt
RPyBeacon.egg-info/dependency_links.txt
RPyBeacon.egg-info/entry_points.txt
RPyBeacon.egg-info/top_level.txt